usdm4_legacy/__info__.py
usdm4_legacy/__init__.py
usdm4_legacy/claude/__init__.py
usdm4_legacy/claude/claude.py
usdm4_legacy/import_/__init__.py
usdm4_legacy/import_/legacy_import.py
usdm4_legacy/import_/assemble/__init__.py
usdm4_legacy/import_/extract/__init__.py
usdm4_legacy/import_/extract/title_page.py
usdm4_legacy/import_/load/__init__.py
usdm4_legacy/import_/load/clean_html.py
usdm4_legacy/import_/load/split_html.py
usdm4_legacy/import_/load/to_html.py
usdm4_legacy-0.1.0a3.dist-info/licenses/LICENSE
usdm4_legacy-0.1.0a3.dist-info/METADATA
usdm4_legacy-0.1.0a3.dist-info/WHEEL
usdm4_legacy-0.1.0a3.dist-info/top_level.txt
usdm4_legacy-0.1.0a3.dist-info/RECORD
