Metadata-Version: 2.4
Name: usdm4_legacy
Version: 0.1.0a3
Summary: A package for processing TransCelerate CPT protocol documents and converting them to USDM format
Author: D Iberson-Hurst
Author-email: 
Classifier: Intended Audience :: Developers
Classifier: Programming Language :: Python
Classifier: Programming Language :: Python :: 3
Classifier: Programming Language :: Python :: 3.12
Classifier: Operating System :: OS Independent
Requires-Python: >=3.12
License-File: LICENSE
Requires-Dist: usdm4>=0.9.0
Requires-Dist: docling==2.43.0
Requires-Dist: anthropic==0.62.0
Requires-Dist: d4k-ms-base>=0.3.0
Dynamic: author
Dynamic: classifier
Dynamic: description
Dynamic: description-content-type
Dynamic: license-file
Dynamic: requires-dist
Dynamic: requires-python
Dynamic: summary
